LICENSE
README.md
setup.cfg
setup.py
PyFiveSim.egg-info/PKG-INFO
PyFiveSim.egg-info/SOURCES.txt
PyFiveSim.egg-info/dependency_links.txt
PyFiveSim.egg-info/not-zip-safe
PyFiveSim.egg-info/requires.txt
PyFiveSim.egg-info/top_level.txt
pyfivesim/__init__.py
pyfivesim/exceptions.py
pyfivesim/clients/__init__.py
pyfivesim/clients/async_client.py
pyfivesim/clients/base.py
pyfivesim/clients/sync_client.py
pyfivesim/clients/request/__init__.py
pyfivesim/clients/request/aiohttp.py
pyfivesim/clients/request/base.py
pyfivesim/clients/request/httpx.py
pyfivesim/enums/__init__.py
pyfivesim/enums/actions.py
pyfivesim/enums/base.py
pyfivesim/enums/base_values.py
pyfivesim/enums/categories.py
pyfivesim/enums/statuses.py
pyfivesim/enums/vendor_withdraw.py
pyfivesim/enums/request/__init__.py
pyfivesim/enums/request/connection.py
pyfivesim/enums/request/method.py
pyfivesim/models/__init__.py
pyfivesim/models/guest/__init__.py
pyfivesim/models/guest/countries.py
pyfivesim/models/guest/prices.py
pyfivesim/models/guest/products.py
pyfivesim/models/request/__init__.py
pyfivesim/models/request/headers.py
pyfivesim/models/user/__init__.py
pyfivesim/models/user/orders.py
pyfivesim/models/user/payments.py
pyfivesim/models/user/price_limits.py
pyfivesim/models/user/profile.py
pyfivesim/models/vendor/__init__.py
pyfivesim/models/vendor/orders.py
pyfivesim/models/vendor/payments.py
pyfivesim/models/vendor/payoff.py
pyfivesim/models/vendor/profile.py
pyfivesim/models/vendor/wallet.py
pyfivesim/utils/__init__.py
pyfivesim/utils/exception_checker.py
pyfivesim/utils/generators.py
pyfivesim/utils/validators.py