Metadata-Version: 2.1
Name: PyFiveSim
Version: 1.0.0
Summary: Sync/async Python wrapper for 5sim API
Home-page: https://github.com/Belyashik2K/PyFiveSim
Author: Belyashik2K
Author-email: work@belyashik2k.ru
License: MIT license
License-File: LICENSE
